Metadata-Version: 1.1
Name: django-typograph
Version: 0.1.1
Summary: Типограф для Django
Home-page: https://github.com/pypa/django_typograph
Author: Xacce
Author-email: thiscie@gmail.com
License: MIT
Keywords: r,u,s,s,i,a,n, ,t,y,p,o,g,r,a,p,h, ,l,a,n,g,u,a,g,e
Platform: UNKNOWN
Classifier: Development Status :: 4 - Beta
Classifier: Intended Audience :: Developers
Classifier: License :: OSI Approved :: MIT License
Classifier: Programming Language :: Python :: 2.6
Classifier: Programming Language :: Python :: 2.7
Requires: django (>= 1.7)
Requires: progressbar2
